hdf5_matlab_reader
